Metadata-Version: 1.2
Name: Pleisthenes
Version: 0.1a0
Summary: Pleisthenes is a weather microservice (connects to a weather site and provides e.g. local sun radiation).
Home-page: https://gitlab.com/pelops/pleisthenes/
Author: Tobias Gawron-Deutsch
Author-email: tobias@strix.at
License: MIT license
Keywords: mqtt service weather
Platform: UNKNOWN
Classifier: Development Status :: 4 - Beta
Classifier: Environment :: Console
Classifier: Environment :: No Input/Output (Daemon)
Classifier: Intended Audience :: Developers
Classifier: Programming Language :: Python :: 3
Classifier: Topic :: Utilities
Classifier: Topic :: Home Automation
Classifier: License :: OSI Approved :: MIT License
Requires-Python: >=3.5
